<?xml version="1.0" encoding="UTF-8"?>
<?xml-stylesheet type='text/xsl' href='_UpgradeReport_Files/UpgradeReport.xslt'?>
<UpgradeLog>
<Properties><Property Name="Solution" Value="Notrip">
</Property><Property Name="Solution File" Value="C:\Documents and Settings\Aidan Fitzpatrick\Desktop\Notrip\Notrip.sln">
</Property><Property Name="Date" Value="08 January 2006">
</Property><Property Name="Time" Value="21:56:29">
</Property><Property Name="Log Number" Value="2">
</Property></Properties><Event ErrorLevel="0" Project="WaveLibMixer" Source="..\WaveLibMixer\WaveLibMixer.csproj" Description="Project converted successfully">
</Event><Event ErrorLevel="3" Project="WaveLibMixer" Source="..\WaveLibMixer\WaveLibMixer.csproj" Description="Converted">
</Event><Event ErrorLevel="0" Project="WaveLibMixer" Source="..\WaveLibMixer\WaveLibMixer.csproj" Description="Scan complete: Upgrade not required for project files.">
</Event></UpgradeLog>
